PySide6VirtualKeyboard/__init__.py
PySide6VirtualKeyboard/keyboard/__init__.py
PySide6VirtualKeyboard/keyboard/virtual_keyboard.py
PySide6VirtualKeyboard/lineEdit/__init__.py
PySide6VirtualKeyboard/lineEdit/virtual_keyboard_lineEdit.py
PySide6VirtualKeyboard/resources/__init__.py
PySide6VirtualKeyboard/resources/resources_rc.py
PySide6VirtualKeyboard/resources/language/__init__.py
PySide6VirtualKeyboard/resources/png/__init__.py
PySide6VirtualKeyboard/resources/vector/__init__.py
PySide6VirtualKeyboard/scrollArea/__init__.py
PySide6VirtualKeyboard/scrollArea/virtual_keyboard_scroll_area.py
PySide6VirtualKeyboard/service/__init__.py
PySide6VirtualKeyboard/ui/__init__.py
PySide6VirtualKeyboard/ui/interface.py
tests/__init__.py
tests/main.py
tests/test.py
tests/test_ui.py
tests/custom_widgets/__init__.py
tests/resources/__init__.py
tests/ui/__init__.py
tests/ui/test_interface.py
pyside6_virtual_keyboard-0.1.5.dist-info/LICENSE
pyside6_virtual_keyboard-0.1.5.dist-info/METADATA
pyside6_virtual_keyboard-0.1.5.dist-info/WHEEL
pyside6_virtual_keyboard-0.1.5.dist-info/top_level.txt
pyside6_virtual_keyboard-0.1.5.dist-info/RECORD
